mat4py/__init__.py
mat4py/cmd.py
mat4py/loadmat.py
mat4py/savemat.py
mat4py-0.4.1.dist-info/DESCRIPTION.rst
mat4py-0.4.1.dist-info/METADATA
mat4py-0.4.1.dist-info/RECORD
mat4py-0.4.1.dist-info/WHEEL
mat4py-0.4.1.dist-info/metadata.json
mat4py-0.4.1.dist-info/top_level.txt
