Metadata-Version: 2.0
Name: mat4py
Version: 0.4.1
Summary: Load and save data in the Matlab (TM) MAT-file format.
Home-page: https://github.com/nephics/mat4py/
Author: Jacob Svensson
Author-email: jacob@nephics.com
License: MIT License
Platform: UNKNOWN
Classifier: Development Status :: 5 - Production/Stable
Classifier: License :: OSI Approved :: MIT License
Classifier: Programming Language :: Python :: 2.7
Classifier: Programming Language :: Python :: 3.4
Classifier: Topic :: Scientific/Engineering
